{
"type": "FeatureCollection",
"features": [
{ "type": "Feature", "properties": { "TEMA": "Jaringan Telekomunikasi Pelayanan", "KODE": "1615", "UNSUR": "layanan telekomunikasi", "NAMA": "", "CATATAN": "11.806 sst" }, "geometry": { "type": "Point", "coordinates": [ 105.904890, -2.076317 ] } }
,
{ "type": "Feature", "properties": { "TEMA": "Jaringan Telekomunikasi Pelayanan", "KODE": "1615", "UNSUR": "Layanan Telekomunikasi", "NAMA": "", "CATATAN": "7.184 sst" }, "geometry": { "type": "Point", "coordinates": [ 105.979922, -1.913628 ] } }
,
{ "type": "Feature", "properties": { "TEMA": "Jaringan Telekomunikasi Pelayanan", "KODE": "1615", "UNSUR": "Layanan Telekomunikasi", "NAMA": "", "CATATAN": "3.956 sst" }, "geometry": { "type": "Point", "coordinates": [ 107.566631, -2.918782 ] } }
,
{ "type": "Feature", "properties": { "TEMA": "Jaringan Telekomunikasi Pelayanan", "KODE": "", "UNSUR": "Layanan Telekomunikasi", "NAMA": "Telkom bangka Selatan", "CATATAN": "Telkomsel, Indosat, Excelmindo" }, "geometry": { "type": "Point", "coordinates": [ 106.462112, -2.979203 ] } }
,
{ "type": "Feature", "properties": { "TEMA": "Jaringan Telkomp", "KODE": "1615", "UNSUR": "Layanan Telekomunikasi", "NAMA": "M. Maning", "CATATAN": "Kapasitas : 10,484 Sst" }, "geometry": { "type": "Point", "coordinates": [ 115.240550, -8.698194 ] } }
,
{ "type": "Feature", "properties": { "TEMA": "Jaringan Telkomp", "KODE": "1615", "UNSUR": "Layanan Telekomunikasi", "NAMA": "Ubung", "CATATAN": "21,218 Sst" }, "geometry": { "type": "Point", "coordinates": [ 115.226488, -8.718904 ] } }
,
{ "type": "Feature", "properties": { "TEMA": "Jaringan Telkomp", "KODE": "1615", "UNSUR": "Layanan Telekomunikasi", "NAMA": "Seminyak", "CATATAN": "Kapasitas : 7,488 Sst" }, "geometry": { "type": "Point", "coordinates": [ 115.102608, -8.834251 ] } }
,
{ "type": "Feature", "properties": { "TEMA": "Jaringan Telkomp", "KODE": "1615", "UNSUR": "Layanan Telekomunikasi", "NAMA": "Lovina", "CATATAN": "Kapasitas : 1,004 Sst" }, "geometry": { "type": "Point", "coordinates": [ 114.826162, -8.201161 ] } }
,
{ "type": "Feature", "properties": { "TEMA": "Jaringan Telkomp", "KODE": "1615", "UNSUR": "Layanan Telekomunikasi", "NAMA": "Dpr-ubud", "CATATAN": "Kapasitas : 11,164" }, "geometry": { "type": "Point", "coordinates": [ 115.253754, -8.470478 ] } }
,
{ "type": "Feature", "properties": { "TEMA": "Jaringan Telkomp", "KODE": "1615", "UNSUR": "Layanan Telekomunikasi", "NAMA": "Dpr-tampaksiring", "CATATAN": "Kapasitas : 1,110 Sst" }, "geometry": { "type": "Point", "coordinates": [ 115.280139, -8.431105 ] } }
,
{ "type": "Feature", "properties": { "TEMA": "Jaringan Telkomp", "KODE": "1615", "UNSUR": "Layanan Telekomunikasi", "NAMA": "Tohpati", "CATATAN": "Kapasitas : 8,308 Sst" }, "geometry": { "type": "Point", "coordinates": [ 115.234853, -8.634373 ] } }
,
{ "type": "Feature", "properties": { "TEMA": "Jaringan Telkomp", "KODE": "1615", "UNSUR": "Layanan Telekomunikasi", "NAMA": "Tabanan", "CATATAN": "Kapasitas : 11,902 Sst" }, "geometry": { "type": "Point", "coordinates": [ 115.109262, -8.549154 ] } }
,
{ "type": "Feature", "properties": { "TEMA": "Jaringan Telkomp", "KODE": "1615", "UNSUR": "Layanan Telekomunikasi", "NAMA": "Seririt", "CATATAN": "Kapasitas : 2,146 Sst" }, "geometry": { "type": "Point", "coordinates": [ 114.929985, -8.197117 ] } }
,
{ "type": "Feature", "properties": { "TEMA": "Jaringan Telkomp", "KODE": "1615", "UNSUR": "Layanan Telekomunikasi", "NAMA": "Sukawati", "CATATAN": "Kapasitas : 7,530 Sst" }, "geometry": { "type": "Point", "coordinates": [ 115.279432, -8.566700 ] } }
,
{ "type": "Feature", "properties": { "TEMA": "Jaringan Telkomp", "KODE": "1615", "UNSUR": "Layanan Telekomunikasi", "NAMA": "Semara Pura", "CATATAN": "Kapasitas : 6,318 Sst" }, "geometry": { "type": "Point", "coordinates": [ 115.374316, -8.532876 ] } }
,
{ "type": "Feature", "properties": { "TEMA": "Jaringan Telkomp", "KODE": "1615", "UNSUR": "Layanan Telekomunikasi", "NAMA": "Singaraja", "CATATAN": "Kapaasitas : 10,012 Sst" }, "geometry": { "type": "Point", "coordinates": [ 115.050290, -8.154428 ] } }
,
{ "type": "Feature", "properties": { "TEMA": "Jaringan Telkomp", "KODE": "1615", "UNSUR": "Layanan Telekomunikasi", "NAMA": "Sanur", "CATATAN": "Kapasitas : 9,732 Sst" }, "geometry": { "type": "Point", "coordinates": [ 115.227804, -8.676396 ] } }
,
{ "type": "Feature", "properties": { "TEMA": "Jaringan Telkomp", "KODE": "1615", "UNSUR": "Layanan Telekomunikasi", "NAMA": "Pupuan", "CATATAN": "Kapasitas : 874 Sst" }, "geometry": { "type": "Point", "coordinates": [ 114.980269, -8.323571 ] } }
,
{ "type": "Feature", "properties": { "TEMA": "Jaringan Telkomp", "KODE": "1615", "UNSUR": "Layanan Telekomunikasi", "NAMA": "Negara", "CATATAN": "Kapasitas : 3,818 Sst" }, "geometry": { "type": "Point", "coordinates": [ 114.618207, -8.364726 ] } }
,
{ "type": "Feature", "properties": { "TEMA": "Jaringan Telkomp", "KODE": "1615", "UNSUR": "Layanan Telekomunikasi", "NAMA": "Nusa Dua", "CATATAN": "Kapasitas : 7,864 Sst" }, "geometry": { "type": "Point", "coordinates": [ 115.190214, -8.824128 ] } }
,
{ "type": "Feature", "properties": { "TEMA": "Jaringan Telkomp", "KODE": "1615", "UNSUR": "Layanan Telekomunikasi", "NAMA": "Kuta", "CATATAN": "Kapasitas : 16,338 Sst" }, "geometry": { "type": "Point", "coordinates": [ 115.153848, -8.683979 ] } }
,
{ "type": "Feature", "properties": { "TEMA": "Jaringan Telkomp", "KODE": "1615", "UNSUR": "Layanan Telekomunikasi", "NAMA": "Kintamani", "CATATAN": "Kapasitas : 1,350 Sst" }, "geometry": { "type": "Point", "coordinates": [ 115.322436, -8.258316 ] } }
,
{ "type": "Feature", "properties": { "TEMA": "Jaringan Telkomp", "KODE": "1615", "UNSUR": "Layanan Telekomunikasi", "NAMA": "Jimbaran", "CATATAN": "Kapasitas : 5,760 Sst" }, "geometry": { "type": "Point", "coordinates": [ 115.139023, -8.812900 ] } }
,
{ "type": "Feature", "properties": { "TEMA": "Jaringan Telkomp", "KODE": "1615", "UNSUR": "Layanan Telekomunikasi", "NAMA": "Gilimanuk", "CATATAN": "Kapasitas : 638 Sst" }, "geometry": { "type": "Point", "coordinates": [ 114.451131, -8.173057 ] } }
,
{ "type": "Feature", "properties": { "TEMA": "Jaringan Telkomp", "KODE": "238", "UNSUR": "Layanan Telekomunikasi", "NAMA": "Gianyar", "CATATAN": "Kapasitas : 13,012 Sst" }, "geometry": { "type": "Point", "coordinates": [ 115.330978, -8.549451 ] } }
,
{ "type": "Feature", "properties": { "TEMA": "Jaringan Telkomp", "KODE": "1615", "UNSUR": "Layanan Telekomunikasi", "NAMA": "Denpasar", "CATATAN": "Kapasitas : 35,984 Sst" }, "geometry": { "type": "Point", "coordinates": [ 115.209417, -8.643176 ] } }
,
{ "type": "Feature", "properties": { "TEMA": "Jaringan Telkomp", "KODE": "1615", "UNSUR": "Layanan Telekomunikasi", "NAMA": "Baturiti", "CATATAN": "Kapasitas : 1,120 Sst" }, "geometry": { "type": "Point", "coordinates": [ 115.138948, -8.300913 ] } }
,
{ "type": "Feature", "properties": { "TEMA": "Jaringan  Telkomp", "KODE": "1615", "UNSUR": "Layanan Telekomunikasi", "NAMA": "Benoa", "CATATAN": "Kapasita : 9,847 Sst" }, "geometry": { "type": "Point", "coordinates": [ 115.177582, -8.726772 ] } }
,
{ "type": "Feature", "properties": { "TEMA": "Jaringan Telkomp", "KODE": "1615", "UNSUR": "Layanan Telekomunikasi", "NAMA": "Bangli", "CATATAN": "Kapasitas : 2,670 Sst" }, "geometry": { "type": "Point", "coordinates": [ 115.332296, -8.465828 ] } }
,
{ "type": "Feature", "properties": { "TEMA": "Jaringan Telkomp", "KODE": "1615", "UNSUR": "Layanan Telekomunikasi", "NAMA": "Amlapura", "CATATAN": "Kapasitas : 2,534 Sst" }, "geometry": { "type": "Point", "coordinates": [ 115.581366, -8.474706 ] } }
,
{ "type": "Feature", "properties": { "TEMA": "Jaringann Telkom Pelayana", "KODE": "1615", "UNSUR": "Kantor Pelayanan Telkom", "NAMA": "", "CATATAN": "Kapasitas 10.060 Sst" }, "geometry": { "type": "Point", "coordinates": [ 106.050103, -6.340806 ] } }
,
{ "type": "Feature", "properties": { "TEMA": "Jaringann Telkom Pelayana", "KODE": "1615", "UNSUR": "Kantor Pelayanan Telkom", "NAMA": "", "CATATAN": "Kapasitas 51.246 Sst" }, "geometry": { "type": "Point", "coordinates": [ 106.203009, -6.177532 ] } }
,
{ "type": "Feature", "properties": { "TEMA": "Jaringann Telkom Pelayana", "KODE": "1615", "UNSUR": "Kantor Pelayanan Telkom", "NAMA": "", "CATATAN": "Kapasitas 11.166 Sst" }, "geometry": { "type": "Point", "coordinates": [ 106.131753, -6.336122 ] } }
,
{ "type": "Feature", "properties": { "TEMA": "Jaringann Telkom Pelayana", "KODE": "1615", "UNSUR": "Kantor Pelayanan Telkom", "NAMA": "", "CATATAN": "Pelayanan 7.040 Sst" }, "geometry": { "type": "Point", "coordinates": [ 106.283016, -6.391459 ] } }
,
{ "type": "Feature", "properties": { "TEMA": "Jaringann Telkom Pelayana", "KODE": "1615", "UNSUR": "Kantor Pelayanan Telkom", "NAMA": "", "CATATAN": "Kapasitas 51.246 Sst" }, "geometry": { "type": "Point", "coordinates": [ 106.190801, -6.147020 ] } }
,
{ "type": "Feature", "properties": { "TEMA": "Jaringan Telekomunikasi Pelayanan", "KODE": "1615", "UNSUR": "Kantor Layanan Telekomunikasi", "NAMA": "", "CATATAN": "Layanan : 3.226 Sst" }, "geometry": { "type": "Point", "coordinates": [ 102.965145, -4.462405 ] } }
,
{ "type": "Feature", "properties": { "TEMA": "Jaringan Telekomunikasi Pelayanan", "KODE": "1615", "UNSUR": "Kantor Layanan Telekomunikasi", "NAMA": "", "CATATAN": "18.019 Sst" }, "geometry": { "type": "Point", "coordinates": [ 102.277508, -3.731781 ] } }
,
{ "type": "Feature", "properties": { "TEMA": "Jaringan Telekomunikasi Pelayanan", "KODE": "1615", "UNSUR": "Kantor Layanan Telekomunikasi", "NAMA": "", "CATATAN": "Kapasitas : 6.333 Sst" }, "geometry": { "type": "Point", "coordinates": [ 102.596620, -3.379341 ] } }
,
{ "type": "Feature", "properties": { "TEMA": "Jaringan Telekomunikasi Pelayanan", "KODE": "1615", "UNSUR": "Kantor Layanan Telekomunikasi", "NAMA": "", "CATATAN": "2.559 Sst" }, "geometry": { "type": "Point", "coordinates": [ 102.179555, -3.408207 ] } }
,
{ "type": "Feature", "properties": { "TEMA": "Jaringan Telkom", "KODE": "1615", "UNSUR": "Layanan Telekomunikasi", "NAMA": "Kantor layanan Telkom Gorontalo", "CATATAN": "Kapasitas 16.700 Sst, Terisi 15.900 Sst" }, "geometry": { "type": "Point", "coordinates": [ 123.115810, 0.542182 ] } }
,
{ "type": "Feature", "properties": { "TEMA": "jaringan telekomunikasi pelayanan", "KODE": "1615", "UNSUR": "Kantor Layanan Telkom", "NAMA": "Muarasabak", "CATATAN": "kapasitas : sst" }, "geometry": { "type": "Point", "coordinates": [ 103.863149, -1.067002 ] } }
,
{ "type": "Feature", "properties": { "TEMA": "jaringan telekomunikasi pelayanan", "KODE": "1615", "UNSUR": "Kantor Layanan Telkom", "NAMA": "Kualatungkal", "CATATAN": "kapasitas : sst" }, "geometry": { "type": "Point", "coordinates": [ 103.540643, -0.838193 ] } }
,
{ "type": "Feature", "properties": { "TEMA": "jaringan telekomunikasi pelayanan", "KODE": "1615", "UNSUR": "Kantor Layanan Telkom", "NAMA": "Muaratebo", "CATATAN": "kapasitas : 2.222 sst" }, "geometry": { "type": "Point", "coordinates": [ 102.449806, -1.511009 ] } }
,
{ "type": "Feature", "properties": { "TEMA": "jar.telkomp", "KODE": "1615", "UNSUR": "Kantor Layanan Telkom", "NAMA": "Muarabulian", "CATATAN": "" }, "geometry": { "type": "Point", "coordinates": [ 103.351156, -1.666444 ] } }
,
{ "type": "Feature", "properties": { "TEMA": "jar.telkomp", "KODE": "1615", "UNSUR": "Kantor Layanan Telkom", "NAMA": "Kota Jambi", "CATATAN": "kapasitas:33.078 sst" }, "geometry": { "type": "Point", "coordinates": [ 103.697652, -1.578089 ] } }
,
{ "type": "Feature", "properties": { "TEMA": "jar.telkomp", "KODE": "1615", "UNSUR": "Kantor Layanan Telkom", "NAMA": "Sengeti", "CATATAN": "kab.sengeti" }, "geometry": { "type": "Point", "coordinates": [ 103.477272, -1.437927 ] } }
,
{ "type": "Feature", "properties": { "TEMA": "jar telkomp", "KODE": "1615", "UNSUR": "Kantor Layanan Telkom", "NAMA": "kab. muarabungo", "CATATAN": "kapasitas:2.594 sst" }, "geometry": { "type": "Point", "coordinates": [ 102.127738, -1.416389 ] } }
,
{ "type": "Feature", "properties": { "TEMA": "jaringan telkom pelayanan", "KODE": "1615", "UNSUR": "Kantor Layanan Telkom", "NAMA": "sungai penuh", "CATATAN": "5.336 sst" }, "geometry": { "type": "Point", "coordinates": [ 101.451896, -2.088725 ] } }
,
{ "type": "Feature", "properties": { "TEMA": "jar telkomp", "KODE": "1615", "UNSUR": "Kantor Layanan Telkom", "NAMA": "kab.sarolangun", "CATATAN": "kapasitas:sst" }, "geometry": { "type": "Point", "coordinates": [ 102.782852, -2.327660 ] } }
,
{ "type": "Feature", "properties": { "TEMA": "jar telkomp", "KODE": "1615", "UNSUR": "Kantor Layanan Telkom", "NAMA": "kab.bangko", "CATATAN": "kapasitas: 2.542 sst" }, "geometry": { "type": "Point", "coordinates": [ 102.199608, -2.039807 ] } }
,
{ "type": "Feature", "properties": { "TEMA": "Telekomunikasi", "KODE": "", "UNSUR": "", "NAMA": "Sragen", "CATATAN": "" }, "geometry": { "type": "Point", "coordinates": [ 111.024385, -7.425587 ] } }
,
{ "type": "Feature", "properties": { "TEMA": "Telekomunikasi", "KODE": "", "UNSUR": "", "NAMA": "Jepara", "CATATAN": "" }, "geometry": { "type": "Point", "coordinates": [ 110.677816, -6.601912 ] } }
,
{ "type": "Feature", "properties": { "TEMA": "Jaringan Telkomp", "KODE": "1615", "UNSUR": "Layanan Telekomunikasi", "NAMA": "Kec. Bengkayang Dan Sunagi Duri", "CATATAN": "layanan 1.308 sst" }, "geometry": { "type": "Point", "coordinates": [ 109.045709, 0.833723 ] } }
,
{ "type": "Feature", "properties": { "TEMA": "Jaringan Telkomp", "KODE": "1615", "UNSUR": "Layanan Telekomunikasi", "NAMA": "Kec. Sambas,tebas Dan Pemangkat", "CATATAN": "layanan 6.340 sst" }, "geometry": { "type": "Point", "coordinates": [ 109.245411, 1.297012 ] } }
,
{ "type": "Feature", "properties": { "TEMA": "Jaringan Telkomp", "KODE": "1615", "UNSUR": "Layanan Telekomunikasi", "NAMA": "Kec Karanagan, Sanggau", "CATATAN": "layanan 3.878 sst" }, "geometry": { "type": "Point", "coordinates": [ 110.505944, 0.059948 ] } }
,
{ "type": "Feature", "properties": { "TEMA": "Jaringan Telkomp", "KODE": "1615", "UNSUR": "Layanan Telekomunikasi", "NAMA": "Putussibau", "CATATAN": "layanan 1.306 sst" }, "geometry": { "type": "Point", "coordinates": [ 112.922937, 0.865618 ] } }
,
{ "type": "Feature", "properties": { "TEMA": "Jaringan Telkomp", "KODE": "1615", "UNSUR": "Layanan Telekomunikasi", "NAMA": "Kec. Sintang", "CATATAN": "layanan 3.682 sst" }, "geometry": { "type": "Point", "coordinates": [ 111.578565, 0.088026 ] } }
,
{ "type": "Feature", "properties": { "TEMA": "Jaringan Telkomp", "KODE": "1615", "UNSUR": "Layanan Telekomunikasi", "NAMA": "Kec. Ketapang Dan Kendawangan", "CATATAN": "layanan 5.148 sst" }, "geometry": { "type": "Point", "coordinates": [ 110.106812, -1.939962 ] } }
,
{ "type": "Feature", "properties": { "TEMA": "Jaringan Telkomp", "KODE": "1615", "UNSUR": "Layanan Telekomunikasi", "NAMA": "Kalimantan Barat", "CATATAN": "" }, "geometry": { "type": "Point", "coordinates": [ 109.291239, -0.149529 ] } }
,
{ "type": "Feature", "properties": { "TEMA": "Jaringan Telkom Pelayanan", "KODE": "1615", "UNSUR": "Layanan Telekomunikasi", "NAMA": "Kotabaru", "CATATAN": "3.850 sst" }, "geometry": { "type": "Point", "coordinates": [ 116.192304, -3.289809 ] } }
,
{ "type": "Feature", "properties": { "TEMA": "Jaringan Telkom Pelayanan", "KODE": "1615", "UNSUR": "Layanan Telekomunikasi", "NAMA": "Kandangan", "CATATAN": "2.408 sst" }, "geometry": { "type": "Point", "coordinates": [ 115.270875, -2.748115 ] } }
,
{ "type": "Feature", "properties": { "TEMA": "Jaringan Telkom Pelayanan", "KODE": "1615", "UNSUR": "Layanan Telekomunikasi", "NAMA": "Barabai", "CATATAN": "1.912 sst" }, "geometry": { "type": "Point", "coordinates": [ 115.474598, -2.553623 ] } }
,
{ "type": "Feature", "properties": { "TEMA": "Jaringan Telkom Pelayanan", "KODE": "1615", "UNSUR": "Layanan Telekomunikasi", "NAMA": "Amuntai", "CATATAN": "1.952 sst" }, "geometry": { "type": "Point", "coordinates": [ 115.291047, -2.415844 ] } }
,
{ "type": "Feature", "properties": { "TEMA": "Jaringan Telkom Pelayanan", "KODE": "1615", "UNSUR": "Layanan Telekomunikasi", "NAMA": "Tanjung", "CATATAN": "2.062 sst" }, "geometry": { "type": "Point", "coordinates": [ 115.364847, -2.113552 ] } }
,
{ "type": "Feature", "properties": { "TEMA": "Jaringan Telkom Pelayanan", "KODE": "", "UNSUR": "Layanan Telekomunikasi", "NAMA": "Prov. Kalimantan Selatan", "CATATAN": "" }, "geometry": { "type": "Point", "coordinates": [ 114.516654, -3.334830 ] } }
,
{ "type": "Feature", "properties": { "TEMA": "Jar_telkomp", "KODE": "1615", "UNSUR": "Layanan Telkom", "NAMA": "Samuda", "CATATAN": "734 sst" }, "geometry": { "type": "Point", "coordinates": [ 112.892363, -2.056109 ] } }
,
{ "type": "Feature", "properties": { "TEMA": "Jar_telkomp", "KODE": "1615", "UNSUR": "Layanan Telkom", "NAMA": "Puruk Cahu", "CATATAN": "792 sst" }, "geometry": { "type": "Point", "coordinates": [ 114.550296, -0.433536 ] } }
,
{ "type": "Feature", "properties": { "TEMA": "Jar_telkomp", "KODE": "1615", "UNSUR": "Layanan Telkom", "NAMA": "Kuala Kurung", "CATATAN": "608 sst" }, "geometry": { "type": "Point", "coordinates": [ 113.652057, -1.118696 ] } }
,
{ "type": "Feature", "properties": { "TEMA": "Jar_telkomp", "KODE": "1615", "UNSUR": "Layanan Telkom", "NAMA": "Kasongan", "CATATAN": "1024 sst" }, "geometry": { "type": "Point", "coordinates": [ 113.155589, -1.772720 ] } }
,
{ "type": "Feature", "properties": { "TEMA": "Jar_telkomp", "KODE": "1615", "UNSUR": "Layanan Telkom", "NAMA": "Kuala Pembuang", "CATATAN": "1022 sst" }, "geometry": { "type": "Point", "coordinates": [ 112.481950, -3.336779 ] } }
,
{ "type": "Feature", "properties": { "TEMA": "Jar_telkomp", "KODE": "1615", "UNSUR": "Layanan Telkom", "NAMA": "Sukamara", "CATATAN": "665 sst" }, "geometry": { "type": "Point", "coordinates": [ 111.153374, -2.798500 ] } }
,
{ "type": "Feature", "properties": { "TEMA": "Jar_telkomp", "KODE": "1615", "UNSUR": "Layanan Telkom", "NAMA": "Muarateweh", "CATATAN": "2689 sst" }, "geometry": { "type": "Point", "coordinates": [ 115.071749, -0.903421 ] } }
,
{ "type": "Feature", "properties": { "TEMA": "Jar_telkomp", "KODE": "1615", "UNSUR": "Layanan Telkom", "NAMA": "Kuala Kuayan", "CATATAN": "578 sst" }, "geometry": { "type": "Point", "coordinates": [ 112.573315, -2.034789 ] } }
,
{ "type": "Feature", "properties": { "TEMA": "Jar_telkomp", "KODE": "1615", "UNSUR": "Layanan Telkom", "NAMA": "Sampit", "CATATAN": "7285 SST" }, "geometry": { "type": "Point", "coordinates": [ 112.611651, -2.668147 ] } }
,
{ "type": "Feature", "properties": { "TEMA": "Jar_telkomp", "KODE": "1615", "UNSUR": "Layanan Telkom", "NAMA": "Kumai", "CATATAN": "1100 SST" }, "geometry": { "type": "Point", "coordinates": [ 111.850956, -2.760854 ] } }
,
{ "type": "Feature", "properties": { "TEMA": "Jar_telkomp", "KODE": "1615", "UNSUR": "Layanan Telkom", "NAMA": "Palangkaraya (Kalteng)", "CATATAN": "17005 sst" }, "geometry": { "type": "Point", "coordinates": [ 113.883998, -2.146185 ] } }
,
{ "type": "Feature", "properties": { "TEMA": "Jaringan Telkomp", "KODE": "1615", "UNSUR": "Layanan Telekomunikasi", "NAMA": "Tanah Grogot", "CATATAN": "Kapasitas Layanan 1.876 Sst" }, "geometry": { "type": "Point", "coordinates": [ 116.111360, -2.033041 ] } }
,
{ "type": "Feature", "properties": { "TEMA": "Jaringan Telkomp", "KODE": "1615", "UNSUR": "Layanan Telekomunikasi", "NAMA": "Samarinda", "CATATAN": "Kapasitas 28.409 Sst" }, "geometry": { "type": "Point", "coordinates": [ 117.151838, -0.659186 ] } }
,
{ "type": "Feature", "properties": { "TEMA": "Jaringan Telkomp", "KODE": "1615", "UNSUR": "Layanan Telekomunikasi", "NAMA": "Bontang", "CATATAN": "Kapasitas 6.565 Sst" }, "geometry": { "type": "Point", "coordinates": [ 117.383535, 0.044576 ] } }
,
{ "type": "Feature", "properties": { "TEMA": "Jaringan Telkomp", "KODE": "1615", "UNSUR": "Layanan Telekomunikasi", "NAMA": "Tenggarong", "CATATAN": "Kapasitas 28.409 Sst" }, "geometry": { "type": "Point", "coordinates": [ 116.969805, -0.413731 ] } }
,
{ "type": "Feature", "properties": { "TEMA": "Jaringan Telkomp", "KODE": "1615", "UNSUR": "Kantor Pelayanan Telkom, Indosat, Exelcomindo,", "NAMA": "Kab. Bintan dan Kota Tanjung Pinang", "CATATAN": "36.768 sst" }, "geometry": { "type": "Point", "coordinates": [ 104.501327, 0.952868 ] } }
,
{ "type": "Feature", "properties": { "TEMA": "Jaringan Telkomp", "KODE": "1615", "UNSUR": "Kantor Telkom", "NAMA": "Tanggamus", "CATATAN": "2.678 SST" }, "geometry": { "type": "Point", "coordinates": [ 104.705883, -5.500397 ] } }
,
{ "type": "Feature", "properties": { "TEMA": "Jaringan Telkomp", "KODE": "1615", "UNSUR": "Kantor Telkom", "NAMA": "Liwa", "CATATAN": "Layanan Telekokomunikasi" }, "geometry": { "type": "Point", "coordinates": [ 104.056596, -5.008745 ] } }
,
{ "type": "Feature", "properties": { "TEMA": "Jaringan Telkomp", "KODE": "1615", "UNSUR": "Kantor Telkom", "NAMA": "Blambangan Umpu", "CATATAN": "" }, "geometry": { "type": "Point", "coordinates": [ 104.562876, -4.556889 ] } }
,
{ "type": "Feature", "properties": { "TEMA": "Jaringan Telkomp", "KODE": "1615", "UNSUR": "Kantor Telkom", "NAMA": "Menggala", "CATATAN": "" }, "geometry": { "type": "Point", "coordinates": [ 105.264668, -4.502820 ] } }
,
{ "type": "Feature", "properties": { "TEMA": "Jaringan Telkomp", "KODE": "1615", "UNSUR": "Kantor Telkom", "NAMA": "Kotabumi", "CATATAN": "" }, "geometry": { "type": "Point", "coordinates": [ 104.862978, -4.870817 ] } }
,
{ "type": "Feature", "properties": { "TEMA": "Jaringan Telkomp", "KODE": "1615", "UNSUR": "Kantor Telkom", "NAMA": "Sukadana", "CATATAN": "" }, "geometry": { "type": "Point", "coordinates": [ 105.516870, -5.093747 ] } }
,
{ "type": "Feature", "properties": { "TEMA": "Jaringan Telkomp", "KODE": "1615", "UNSUR": "Kantor Telkom", "NAMA": "Metro", "CATATAN": "8.699 SST" }, "geometry": { "type": "Point", "coordinates": [ 105.258984, -5.138830 ] } }
,
{ "type": "Feature", "properties": { "TEMA": "Jaringan Telkomp", "KODE": "1615", "UNSUR": "Kantor Telkom", "NAMA": "Gunungsugih", "CATATAN": "3.368 SST" }, "geometry": { "type": "Point", "coordinates": [ 105.239247, -4.992065 ] } }
,
{ "type": "Feature", "properties": { "TEMA": "Jaringan Telkomp", "KODE": "1615", "UNSUR": "Kantor Telkom", "NAMA": "Bandar Lampung", "CATATAN": "61.350 SST" }, "geometry": { "type": "Point", "coordinates": [ 105.336915, -5.461796 ] } }
,
{ "type": "Feature", "properties": { "TEMA": "Jaringan Telkomp", "KODE": "1615", "UNSUR": "Kantor Telkom", "NAMA": "Kalianda", "CATATAN": "3.368 SST" }, "geometry": { "type": "Point", "coordinates": [ 105.608614, -5.734704 ] } }
,
{ "type": "Feature", "properties": { "TEMA": "jaringan telekomunikasi pelayanan", "KODE": "1615", "UNSUR": "kantor pelayanan telekomunikasi", "NAMA": "Kantor Telkom Masohi", "CATATAN": "1.752 sst" }, "geometry": { "type": "Point", "coordinates": [ 129.062150, -3.338506 ] } }
,
{ "type": "Feature", "properties": { "TEMA": "jaringan telekomunikasi pelayanan", "KODE": "1615", "UNSUR": "kantor pelayanan telekomunikasi", "NAMA": "Kantor Telkom Maluku", "CATATAN": "" }, "geometry": { "type": "Point", "coordinates": [ 128.203804, -3.667824 ] } }
,
{ "type": "Feature", "properties": { "TEMA": "", "KODE": "", "UNSUR": "", "NAMA": "", "CATATAN": "" }, "geometry": { "type": "Point", "coordinates": [ 127.427227, 0.694736 ] } }
,
{ "type": "Feature", "properties": { "TEMA": "Jaringan Telkom Pelayanan", "KODE": "1615", "UNSUR": "Kantor Pelayanan Telkom", "NAMA": "Batu Nyale", "CATATAN": "" }, "geometry": { "type": "Point", "coordinates": [ 116.324694, -8.794261 ] } }
,
{ "type": "Feature", "properties": { "TEMA": "Jaringan Telkom Pelayanan", "KODE": "1615", "UNSUR": "Kantor Pelayanan Telkom", "NAMA": "Mataram", "CATATAN": "" }, "geometry": { "type": "Point", "coordinates": [ 116.068753, -8.697758 ] } }
,
{ "type": "Feature", "properties": { "TEMA": "Jaringan Telkom Pelayanan", "KODE": "1615", "UNSUR": "Kantor Pelayanan Telkom", "NAMA": "Sumbawa Besar", "CATATAN": "" }, "geometry": { "type": "Point", "coordinates": [ 117.461540, -8.526121 ] } }
,
{ "type": "Feature", "properties": { "TEMA": "Jaringan Telkom Pelayanan", "KODE": "1615", "UNSUR": "Kantor Pelayanan Telkom", "NAMA": "Dompu", "CATATAN": "" }, "geometry": { "type": "Point", "coordinates": [ 118.509873, -8.596224 ] } }
,
{ "type": "Feature", "properties": { "TEMA": "Jaringan Telkom Pelayanan", "KODE": "1615", "UNSUR": "Kantor Pelayanan Telkom", "NAMA": "Raba", "CATATAN": "" }, "geometry": { "type": "Point", "coordinates": [ 118.837606, -8.509353 ] } }
,
{ "type": "Feature", "properties": { "TEMA": "Jar Telkomp", "KODE": "1615", "UNSUR": "Kantor Pelayanan Telkom P", "NAMA": "Kab.alor", "CATATAN": "904 sst" }, "geometry": { "type": "Point", "coordinates": [ 124.528459, -8.168566 ] } }
,
{ "type": "Feature", "properties": { "TEMA": "Jar Telkomp", "KODE": "1615", "UNSUR": "Kantor Pelayanan Telkom P", "NAMA": "Kab. Flores Timur", "CATATAN": "1.126 sst" }, "geometry": { "type": "Point", "coordinates": [ 122.899283, -8.297166 ] } }
,
{ "type": "Feature", "properties": { "TEMA": "Jar Telkomp", "KODE": "1615", "UNSUR": "Kantor Pelayanan Telkom P", "NAMA": "Kab.sikka", "CATATAN": "2.019 sst" }, "geometry": { "type": "Point", "coordinates": [ 122.218500, -8.685425 ] } }
,
{ "type": "Feature", "properties": { "TEMA": "Jar Telkomp", "KODE": "1615", "UNSUR": "Kantor Pelayanan Telkom P", "NAMA": "Kab.ende", "CATATAN": "2.031 sst" }, "geometry": { "type": "Point", "coordinates": [ 121.599894, -8.802609 ] } }
,
{ "type": "Feature", "properties": { "TEMA": "Jar Telkomp", "KODE": "1615", "UNSUR": "Kantor Pelayanan Telkom P", "NAMA": "Kab,ngada", "CATATAN": "868 sst" }, "geometry": { "type": "Point", "coordinates": [ 120.983261, -8.779093 ] } }
,
{ "type": "Feature", "properties": { "TEMA": "Jar Telkomp", "KODE": "1615", "UNSUR": "Kantor Pelayanan Telkom P", "NAMA": "Manggarai", "CATATAN": "1.375 sst" }, "geometry": { "type": "Point", "coordinates": [ 120.430557, -8.566313 ] } }
,
{ "type": "Feature", "properties": { "TEMA": "Jar Telkomp", "KODE": "1615", "UNSUR": "Kantor Pelayanan Telkom P", "NAMA": "Sumba Barat", "CATATAN": "1.027 sst" }, "geometry": { "type": "Point", "coordinates": [ 119.284026, -9.612850 ] } }
,
{ "type": "Feature", "properties": { "TEMA": "Jar Telkomp", "KODE": "1615", "UNSUR": "Kantor Pelayanan Telkom P", "NAMA": "Sumba Timur", "CATATAN": "1.770 sst" }, "geometry": { "type": "Point", "coordinates": [ 120.207333, -9.718965 ] } }
,
{ "type": "Feature", "properties": { "TEMA": "Jar Telkomp", "KODE": "1615", "UNSUR": "Kantor Pelayanan Telkom P", "NAMA": "Kab.kupang", "CATATAN": "20.034 sst" }, "geometry": { "type": "Point", "coordinates": [ 123.678017, -10.192032 ] } }
,
{ "type": "Feature", "properties": { "TEMA": "Jar Telkomp", "KODE": "1615", "UNSUR": "Kantor Pelayanan Telkom P", "NAMA": "Timor Tengah Selatan", "CATATAN": "1.619 sst" }, "geometry": { "type": "Point", "coordinates": [ 124.316697, -9.908723 ] } }
,
{ "type": "Feature", "properties": { "TEMA": "Jar Telkomp", "KODE": "1615", "UNSUR": "Kantor Pelayanan Telkom P", "NAMA": "Timor Tengah Utara", "CATATAN": "874 sst" }, "geometry": { "type": "Point", "coordinates": [ 124.418827, -9.437288 ] } }
,
{ "type": "Feature", "properties": { "TEMA": "Jar Telkomp", "KODE": "1615", "UNSUR": "Kantor Pelayanan Telkom P", "NAMA": "Belu", "CATATAN": "7.766 sst" }, "geometry": { "type": "Point", "coordinates": [ 124.969403, -9.184301 ] } }
,
{ "type": "Feature", "properties": { "TEMA": "Jaringan Telkomp", "KODE": "1615", "UNSUR": "Kantor Pelayanan Telkom", "NAMA": "", "CATATAN": "Kapasitas 3.026 Sst" }, "geometry": { "type": "Point", "coordinates": [ 103.034119, -0.479095 ] } }
,
{ "type": "Feature", "properties": { "TEMA": "Jaringan Telkomp", "KODE": "1615", "UNSUR": "Kantor Pelayanan Telkom", "NAMA": "", "CATATAN": "Kapasitas 3.106 Sst" }, "geometry": { "type": "Point", "coordinates": [ 102.496467, -0.312273 ] } }
,
{ "type": "Feature", "properties": { "TEMA": "Jaringan Telkomp", "KODE": "1615", "UNSUR": "Kantor Pelayanan Telkom", "NAMA": "", "CATATAN": "Kapasitas 13.760 Sst" }, "geometry": { "type": "Point", "coordinates": [ 101.356276, 0.592282 ] } }
,
{ "type": "Feature", "properties": { "TEMA": "Jaringan Telkomp", "KODE": "1615", "UNSUR": "Kantor Pelayanan Telkom", "NAMA": "", "CATATAN": "Kapasitas 7.116 Sst" }, "geometry": { "type": "Point", "coordinates": [ 100.937717, 0.259278 ] } }
,
{ "type": "Feature", "properties": { "TEMA": "Jaringan Telkomp", "KODE": "1615", "UNSUR": "Kantor Pelayanan Telkom", "NAMA": "Bengalis", "CATATAN": "Kapasitas 13.480 Sst" }, "geometry": { "type": "Point", "coordinates": [ 102.187558, 1.484160 ] } }
,
{ "type": "Feature", "properties": { "TEMA": "Jaringan Telkomp", "KODE": "1615", "UNSUR": "Kantor Pelayanan Telkom", "NAMA": "", "CATATAN": "Kapasitas 7108 Sst" }, "geometry": { "type": "Point", "coordinates": [ 101.400837, 1.531645 ] } }
,
{ "type": "Feature", "properties": { "TEMA": "Jaringan telkom pelayanan", "KODE": "1615", "UNSUR": "Layanan telekomunikasi", "NAMA": "Banggai", "CATATAN": "779 SST" }, "geometry": { "type": "Point", "coordinates": [ 123.397179, -1.661169 ] } }
,
{ "type": "Feature", "properties": { "TEMA": "Jaringan telkom pelayanan", "KODE": "1615", "UNSUR": "Layanan telekomunikasi", "NAMA": "Luwuk", "CATATAN": "5.316 SST" }, "geometry": { "type": "Point", "coordinates": [ 122.568516, -1.123213 ] } }
,
{ "type": "Feature", "properties": { "TEMA": "Jaringan telkom pelayanan", "KODE": "1615", "UNSUR": "Layanan telekomunikasi", "NAMA": "Poso", "CATATAN": "5.700 SST" }, "geometry": { "type": "Point", "coordinates": [ 120.595720, -1.484836 ] } }
,
{ "type": "Feature", "properties": { "TEMA": "Jaringan telkom pelayanan", "KODE": "1615", "UNSUR": "Layanan telekomunikasi", "NAMA": "Parigi", "CATATAN": "2.195 SST" }, "geometry": { "type": "Point", "coordinates": [ 120.206263, -0.928197 ] } }
,
{ "type": "Feature", "properties": { "TEMA": "Jaringan telkom pelayanan", "KODE": "1615", "UNSUR": "Layanan telekomunikasi", "NAMA": "Kec. Banawa dan Kec. Tawaeli", "CATATAN": "2.278 SST" }, "geometry": { "type": "Point", "coordinates": [ 119.578559, -0.774823 ] } }
,
{ "type": "Feature", "properties": { "TEMA": "Jaringan telkom pelayanan", "KODE": "1615", "UNSUR": "Layanan telekomunikasi", "NAMA": "Tolitoli", "CATATAN": "2.500 SST" }, "geometry": { "type": "Point", "coordinates": [ 120.721103, 1.008198 ] } }
,
{ "type": "Feature", "properties": { "TEMA": "Jaringan telkom pelayanan", "KODE": "1615", "UNSUR": "Layanan telekomunikasi", "NAMA": "Sulawesi Tengah", "CATATAN": "" }, "geometry": { "type": "Point", "coordinates": [ 119.800337, -0.859109 ] } }
,
{ "type": "Feature", "properties": { "TEMA": "Jaringan Telkom", "KODE": "1615", "UNSUR": "Kantor Pelayanan Telekomunikasi", "NAMA": "", "CATATAN": "Kendari 16680 Sst" }, "geometry": { "type": "Point", "coordinates": [ 122.596845, -3.928761 ] } }
,
{ "type": "Feature", "properties": { "TEMA": "Jaringan Telkom", "KODE": "1615", "UNSUR": "Kantor Pelayanan Telekomunikasi", "NAMA": "", "CATATAN": "Unahaa 2754 Sst" }, "geometry": { "type": "Point", "coordinates": [ 122.057631, -3.928542 ] } }
,
{ "type": "Feature", "properties": { "TEMA": "Jaringan Telkom", "KODE": "1615", "UNSUR": "Kantor Pelayanan Telekomunikasi", "NAMA": "", "CATATAN": "Andoolo 2330 Sst" }, "geometry": { "type": "Point", "coordinates": [ 122.123008, -4.126306 ] } }
,
{ "type": "Feature", "properties": { "TEMA": "Jaringan Telkom", "KODE": "1615", "UNSUR": "Kantor Pelayanan Telekomunikasi", "NAMA": "", "CATATAN": "Kolaka 2686 Sst" }, "geometry": { "type": "Point", "coordinates": [ 121.653640, -4.137437 ] } }
,
{ "type": "Feature", "properties": { "TEMA": "Jaringan Telkom", "KODE": "1615", "UNSUR": "Kantor Pelayanan Telekomunikasi", "NAMA": "", "CATATAN": "Raha 3464 Sst" }, "geometry": { "type": "Point", "coordinates": [ 122.666069, -4.880802 ] } }
,
{ "type": "Feature", "properties": { "TEMA": "Jaringan Telkom", "KODE": "1615", "UNSUR": "Kantor Pelayanan Telekomunikasi", "NAMA": "", "CATATAN": "Kab Buton 6850 Sst" }, "geometry": { "type": "Point", "coordinates": [ 122.653243, -5.458647 ] } }
,
{ "type": "Feature", "properties": { "TEMA": "Jaringan Telkom Sumut", "KODE": "1915", "UNSUR": "Telkomsel, Indosat, Exelcomindo", "NAMA": "", "CATATAN": "103000 SST terpakai 89100" }, "geometry": { "type": "Point", "coordinates": [ 124.824610, 1.444186 ] } }
,
{ "type": "Feature", "properties": { "TEMA": "Jaringan Telkom", "KODE": "1615", "UNSUR": "Kantor Pelayanan Telkom", "NAMA": "", "CATATAN": "Kab 50kota 1668 Sst" }, "geometry": { "type": "Point", "coordinates": [ 100.582993, -0.159224 ] } }
,
{ "type": "Feature", "properties": { "TEMA": "Jaringan Telkom", "KODE": "1615", "UNSUR": "Kantor Pelayanan Telkom", "NAMA": "", "CATATAN": "Kab Tanah Datar 2460 Sst" }, "geometry": { "type": "Point", "coordinates": [ 100.544499, -0.488469 ] } }
,
{ "type": "Feature", "properties": { "TEMA": "Jaringan Telkom", "KODE": "1615", "UNSUR": "Kantor Pelayanan Telkom", "NAMA": "", "CATATAN": "Kab Sawah Lunto 1520 Sst" }, "geometry": { "type": "Point", "coordinates": [ 101.032883, -0.612811 ] } }
,
{ "type": "Feature", "properties": { "TEMA": "Jaringan Telkom", "KODE": "1615", "UNSUR": "Kantor Pelayanan Telkom", "NAMA": "", "CATATAN": "Kodya Sawahlunto 2370 Sst" }, "geometry": { "type": "Point", "coordinates": [ 100.773073, -0.574957 ] } }
,
{ "type": "Feature", "properties": { "TEMA": "Jaringan Telkom", "KODE": "1615", "UNSUR": "Kantor Pelayanan Telkom", "NAMA": "", "CATATAN": "Kab Solok 6658 Sst" }, "geometry": { "type": "Point", "coordinates": [ 100.662323, -0.809820 ] } }
,
{ "type": "Feature", "properties": { "TEMA": "Jaringan Telkom", "KODE": "1615", "UNSUR": "Kantor Pelayanan Telkom", "NAMA": "", "CATATAN": "Kab Pasaman 2498 Sst" }, "geometry": { "type": "Point", "coordinates": [ 100.168149, 0.053990 ] } }
,
{ "type": "Feature", "properties": { "TEMA": "Jaringan Telkom", "KODE": "1615", "UNSUR": "Kantor Pelayanan Telkom", "NAMA": "", "CATATAN": "Kab Pesisir Selatan 1440 Sst" }, "geometry": { "type": "Point", "coordinates": [ 100.623461, -1.360788 ] } }
,
{ "type": "Feature", "properties": { "TEMA": "Jaringan Telkom", "KODE": "1615", "UNSUR": "Kantor Pelayanan Telkom", "NAMA": "", "CATATAN": "Kodya Padang 41882 Sst" }, "geometry": { "type": "Point", "coordinates": [ 100.468865, -0.998052 ] } }
,
{ "type": "Feature", "properties": { "TEMA": "Jaringan Telkom", "KODE": "1615", "UNSUR": "Kantor Pelayanan Telkom", "NAMA": "", "CATATAN": "Kodya Payakumbuh 6420 Sst" }, "geometry": { "type": "Point", "coordinates": [ 100.649269, -0.291494 ] } }
,
{ "type": "Feature", "properties": { "TEMA": "Jaringan Telkom", "KODE": "1615", "UNSUR": "Kantor Pelayanan Telkom", "NAMA": "", "CATATAN": "Kab Padang Pariaman 4178 Sst" }, "geometry": { "type": "Point", "coordinates": [ 100.119189, -0.584292 ] } }
,
{ "type": "Feature", "properties": { "TEMA": "Jaringan Telkom", "KODE": "1615", "UNSUR": "Kantor Pelayanan Telkom", "NAMA": "", "CATATAN": "Kodya Bukitinggi 7814 Sst" }, "geometry": { "type": "Point", "coordinates": [ 100.324777, -0.361287 ] } }
,
{ "type": "Feature", "properties": { "TEMA": "Jaringan Telkom", "KODE": "1615", "UNSUR": "Kantor Pelayanan Telkom", "NAMA": "", "CATATAN": "Kodya Padangpanjang 2346 Sst" }, "geometry": { "type": "Point", "coordinates": [ 100.404217, -0.496491 ] } }
,
{ "type": "Feature", "properties": { "TEMA": "Jaringan Telkom", "KODE": "1615", "UNSUR": "Kantor Pelayanan Telkom", "NAMA": "", "CATATAN": "Kab Agam 2780 Sst" }, "geometry": { "type": "Point", "coordinates": [ 100.085563, -0.284215 ] } }
,
{ "type": "Feature", "properties": { "TEMA": "Kantor Pelayanan", "KODE": "1615", "UNSUR": "Kantor Pelayanan Telekomunikasi", "NAMA": "", "CATATAN": "Lokasi Muara Dua" }, "geometry": { "type": "Point", "coordinates": [ 104.039895, -4.582157 ] } }
,
{ "type": "Feature", "properties": { "TEMA": "Kantor Pelayanan", "KODE": "1615", "UNSUR": "Kantor Pelayanan Telekomunikasi", "NAMA": "", "CATATAN": "Lokasi Lubuk Linggau, Tugu Mulyo" }, "geometry": { "type": "Point", "coordinates": [ 103.005079, -3.255967 ] } }
,
{ "type": "Feature", "properties": { "TEMA": "Kantor Pelayanan", "KODE": "1615", "UNSUR": "Kantor Pelayanan Telekomunikasi", "NAMA": "", "CATATAN": "Lokasi Muara Enim, Tanjung Enim, Prabumulih" }, "geometry": { "type": "Point", "coordinates": [ 103.756734, -3.591641 ] } }
,
{ "type": "Feature", "properties": { "TEMA": "Kantor Pelayanan", "KODE": "1615", "UNSUR": "Kantor Pelayanan Telekomunikasi", "NAMA": "", "CATATAN": "Lokasi Pagar Alam" }, "geometry": { "type": "Point", "coordinates": [ 103.303636, -4.056324 ] } }
,
{ "type": "Feature", "properties": { "TEMA": "Kantor Pelayanan", "KODE": "1615", "UNSUR": "Kantor Pelayanan Telekomunikasi", "NAMA": "", "CATATAN": "Lokasi Lahat, Tebing Tinggi" }, "geometry": { "type": "Point", "coordinates": [ 103.501916, -3.850232 ] } }
,
{ "type": "Feature", "properties": { "TEMA": "Kantor Pelayanan", "KODE": "1615", "UNSUR": "Kantor Pelayanan Telekomunikasi", "NAMA": "", "CATATAN": "Lokasi Sekayu, Babat Toman, Bayung Lincir" }, "geometry": { "type": "Point", "coordinates": [ 103.853241, -2.853768 ] } }
,
{ "type": "Feature", "properties": { "TEMA": "Kantor Pelayanan", "KODE": "1615", "UNSUR": "Kantor Pelayanan Telekomunikasi", "NAMA": "", "CATATAN": "Lokasi Pangkalan Balai, Betung, Sungsang" }, "geometry": { "type": "Point", "coordinates": [ 104.293417, -2.865364 ] } }
,
{ "type": "Feature", "properties": { "TEMA": "Kantor Pelayanan", "KODE": "1615", "UNSUR": "Kantor Pelayanan Telekomunikasi", "NAMA": "", "CATATAN": "Lokasi Kayu Agung, Tanjung Batu, Tugu Mulyo" }, "geometry": { "type": "Point", "coordinates": [ 104.745755, -3.500536 ] } }
,
{ "type": "Feature", "properties": { "TEMA": "Kantor Pelayanan", "KODE": "1615", "UNSUR": "Kantor Pelayanan Telekomunikasi", "NAMA": "", "CATATAN": "Lokasi Indralaya, Tanjung Raja" }, "geometry": { "type": "Point", "coordinates": [ 104.731475, -3.327913 ] } }
,
{ "type": "Feature", "properties": { "TEMA": "Kantor Pelayanan", "KODE": "1615", "UNSUR": "Kantor Pelayanan Telekomunikasi", "NAMA": "", "CATATAN": "Lokasi Jl. Merdeka, Jl. Kap. Rivai, Kenten, Talang Kelapa, Jl. Sudirman (plaza Telkom)" }, "geometry": { "type": "Point", "coordinates": [ 104.770822, -3.123977 ] } }
,
{ "type": "Feature", "properties": { "TEMA": "Kantor Pelayanan", "KODE": "", "UNSUR": "Kantor Pelayanan Telekomunikasi", "NAMA": "", "CATATAN": "Sungsang" }, "geometry": { "type": "Point", "coordinates": [ 104.854981, -2.348001 ] } }
,
{ "type": "Feature", "properties": { "TEMA": "Kantor Pelayanan", "KODE": "", "UNSUR": "Kantor Pelayanan Telekomunikasi", "NAMA": "", "CATATAN": "Pangkalan Balai" }, "geometry": { "type": "Point", "coordinates": [ 104.366191, -2.928059 ] } }
,
{ "type": "Feature", "properties": { "TEMA": "Jar Telkomp", "KODE": "1615", "UNSUR": "Layanan Telekomunikasi", "NAMA": "Kodya Binjai", "CATATAN": "13.050 sst" }, "geometry": { "type": "Point", "coordinates": [ 98.248371, 3.686694 ] } }
,
{ "type": "Feature", "properties": { "TEMA": "Jar Telkomp", "KODE": "1615", "UNSUR": "Layanan Telekomunikasi", "NAMA": "Tebingtinggi", "CATATAN": "306.128 sst" }, "geometry": { "type": "Point", "coordinates": [ 99.186985, 3.275572 ] } }
,
{ "type": "Feature", "properties": { "TEMA": "Jar Telkomp", "KODE": "1615", "UNSUR": "Layanan Telekomunikasi", "NAMA": "Tanjungbalai", "CATATAN": "6.292 sst" }, "geometry": { "type": "Point", "coordinates": [ 99.703851, 2.978566 ] } }
,
{ "type": "Feature", "properties": { "TEMA": "Jar Telkomp", "KODE": "1615", "UNSUR": "Layanan Telekomunikasi", "NAMA": "Pematangsiantar", "CATATAN": "14.294 sst" }, "geometry": { "type": "Point", "coordinates": [ 99.210189, 2.927668 ] } }
,
{ "type": "Feature", "properties": { "TEMA": "Jar Telkomp", "KODE": "1615", "UNSUR": "Layanan Telekomunikasi", "NAMA": "Kabanjahe", "CATATAN": "5.400 sst" }, "geometry": { "type": "Point", "coordinates": [ 98.416378, 3.159945 ] } }
,
{ "type": "Feature", "properties": { "TEMA": "Jar Telkomp", "KODE": "1615", "UNSUR": "Layanan Telekomunikasi", "NAMA": "Dairi", "CATATAN": "3.556 sst" }, "geometry": { "type": "Point", "coordinates": [ 98.254175, 2.702744 ] } }
,
{ "type": "Feature", "properties": { "TEMA": "Jar Telkomp", "KODE": "1615", "UNSUR": "Layanan Telekomunikasi", "NAMA": "Rantauprapat", "CATATAN": "4.692 sst" }, "geometry": { "type": "Point", "coordinates": [ 99.915816, 1.988814 ] } }
,
{ "type": "Feature", "properties": { "TEMA": "Jar Telkomp", "KODE": "1615", "UNSUR": "Layanan Telekomunikasi", "NAMA": "Tarutung", "CATATAN": "7.844 sst" }, "geometry": { "type": "Point", "coordinates": [ 98.850973, 1.995770 ] } }
,
{ "type": "Feature", "properties": { "TEMA": "Jar Telkomp", "KODE": "1615", "UNSUR": "Layanan Telekomunikasi", "NAMA": "Sibolga", "CATATAN": "4.000 sst" }, "geometry": { "type": "Point", "coordinates": [ 98.737061, 1.901875 ] } }
,
{ "type": "Feature", "properties": { "TEMA": "Jar Telkomp", "KODE": "1615", "UNSUR": "Layanan Telekomunikasi", "NAMA": "Padangsidempuan", "CATATAN": "1.632 sst" }, "geometry": { "type": "Point", "coordinates": [ 99.303946, 1.326076 ] } }
,
{ "type": "Feature", "properties": { "TEMA": "Jar Telkomp", "KODE": "1615", "UNSUR": "Layanan Telekomunikasi", "NAMA": "Gunungsitoli", "CATATAN": "2.248 sst" }, "geometry": { "type": "Point", "coordinates": [ 97.486140, 1.309757 ] } }
,
{ "type": "Feature", "properties": { "TEMA": "", "KODE": "", "UNSUR": "", "NAMA": "Telkom Sibolga", "CATATAN": "4.000 sst" }, "geometry": { "type": "Point", "coordinates": [ 98.800156, 1.766564 ] } }

]
}
